pynova/__init__.py
pynova/power.py
pynova-0.0.4.dist-info/LICENSE
pynova-0.0.4.dist-info/METADATA
pynova-0.0.4.dist-info/WHEEL
pynova-0.0.4.dist-info/top_level.txt
pynova-0.0.4.dist-info/RECORD
