Metadata-Version: 2.1
Name: pynova
Version: 0.0.4
Summary: An easy Python alternative to R functions relating to ANOVA
Home-page: https://github.com/joshegladwell/pynova
Author: Joshua Gladwell
Author-email: joshegladwell@gmail.com
License: UNKNOWN
Project-URL: Bug Tracker, https://github.com/joshegladwell/pynova/issues
Platform: UNKNOWN
Classifier: Programming Language :: Python :: 3
Classifier: License :: OSI Approved :: MIT License
Classifier: Operating System :: OS Independent
Requires-Python: >=3.6
License-File: LICENSE
